LICENSE.txt
README.md
setup.cfg
setup.py
GoldenChild/__init__.py
GoldenChild/xpath.py
GoldenChild.egg-info/PKG-INFO
GoldenChild.egg-info/SOURCES.txt
GoldenChild.egg-info/dependency_links.txt
GoldenChild.egg-info/requires.txt
GoldenChild.egg-info/top_level.txt
bin/validate.py
bin/xget.py
bin/xset.py