Metadata-Version: 2.1
Name: GoldenChild
Version: 1.16
Summary: UNKNOWN
Home-page: https://github.com/eddo888/GoldenChild
Author: David Edson
Author-email: eddo888@tpg.com.au
License: MIT
Download-URL: https://github.com/eddo888/GoldenChild/archive/1.16.tar.gz
Platform: UNKNOWN
License-File: LICENSE.txt
